CHANGES.txt
MANIFEST.in
README.txt
setup.py
src/rsl/__init__.py
src/rsl.mime.egg-info/PKG-INFO
src/rsl.mime.egg-info/SOURCES.txt
src/rsl.mime.egg-info/dependency_links.txt
src/rsl.mime.egg-info/entry_points.txt
src/rsl.mime.egg-info/namespace_packages.txt
src/rsl.mime.egg-info/requires.txt
src/rsl.mime.egg-info/top_level.txt
src/rsl/mime/__init__.py
src/rsl/mime/factories.py
src/rsl/mime/namespace.py
src/rsl/mime/schema.py
src/rsl/mime/serializer.py
src/rsl/mime/wsdl1.py
src/rsl/mime/xsds/wsdlmime.xsd